{
	"miniprogramRoot": "miniprogram/",
	"cloudfunctionRoot": "cloudfunctions/",
	"setting": {
		"urlCheck": false,
		"es6": true,
		"enhance": true,
		"postcss": true,
		"minified": true,
		"newFeature": true,
		"coverView": true,
		"autoAudits": false,
		"showShadowRootInWxmlPanel": true,
		"scopeDataCheck": false,
		"checkInvalidKey": true,
		"checkSiteMap": true,
		"uploadWithSourceMap": true,
		"babelSetting": {
			"ignore": [],
			"disablePlugins": [],
			"outputPath": ""
		},
		"nodeModules": true,
		"bundle": false
	},
	"appid": "wx1010f5d30a0d43ed",
	"projectname": "wechat-mp",
	"libVersion": "2.11.0",
	"cloudfunctionTemplateRoot": "cloudfunctionTemplate",
	"simulatorType": "wechat",
	"simulatorPluginLibVersion": {},
	"condition": {
		"search": {
			"current": -1,
			"list": []
		},
		"conversation": {
			"current": -1,
			"list": []
		},
		"plugin": {
			"current": -1,
			"list": []
		},
		"game": {
			"list": []
		},
		"gamePlugin": {
			"current": -1,
			"list": []
		},
		"miniprogram": {
			"current": -1,
			"list": [
				{
					"id": 1,
					"name": "设置",
					"pathName": "pages/setting/setting",
					"query": "",
					"scene": null
				},
				{
					"id": 2,
					"name": "工具",
					"pathName": "pages/tools/tools",
					"query": "",
					"scene": null
				},
				{
					"id": 2,
					"name": "统计",
					"pathName": "pages/statistics/statistics",
					"query": "",
					"scene": null
				},
				{
					"id": 3,
					"name": "用户-分类管理",
					"pathName": "pages/setting/classManage/classManage",
					"query": "",
					"scene": null
				},
				{
					"id": 4,
					"name": "用户-记账",
					"pathName": "pages/index/bookkeep/bookkeep",
					"query": "",
					"scene": null
				},
				{
					"id": 7,
					"name": "管理员-分类管理",
					"pathName": "pages/admin/classManage/classManage",
					"query": "",
					"scene": null
				},
				{
					"id": 8,
					"name": "管理员-添加分类",
					"pathName": "pages/admin/addClass/addClass",
					"query": "",
					"scene": null
				},
				{
					"id": -1,
					"name": "图片上传",
					"pathName": "pages/admin/upload/upload",
					"query": "",
					"scene": null
				},
				{
					"id": -1,
					"name": "账目详情",
					"pathName": "pages/accountDetail/accountDetail",
					"query": "",
					"scene": null
				},
				{
					"id": -1,
					"name": "管理员 - 启动页设置",
					"pathName": "pages/admin/setWelcome/setWelcome",
					"query": "",
					"scene": null
				},
				{
					"id": -1,
					"name": "关于",
					"pathName": "pages/about/about",
					"query": "",
					"scene": null
				},
				{
					"id": -1,
					"name": "高级设置",
					"pathName": "pages/personalSetting/personalSetting",
					"query": "",
					"scene": null
				},
				{
					"id": 12,
					"name": "AA记账 - 首页",
					"pathName": "pages/tools/AA/index/index",
					"query": "",
					"scene": null
				},
				{
					"id": -1,
					"name": "AA记账 - 邀请",
					"pathName": "pages/tools/AA/invite/invite",
					"query": "",
					"scene": null
				},
				{
					"id": -1,
					"name": "AA记账 - 成员列表",
					"pathName": "pages/tools/AA/member/member",
					"query": "",
					"scene": null
				},
				{
					"id": 15,
					"name": "AA记账 - 索引列表",
					"pathName": "pages/tools/AA/indexList/indexList",
					"scene": null
				},
				{
					"id": -1,
					"name": "AA记账 - 结算",
					"pathName": "pages/tools/AA/settle/settle",
					"query": "",
					"scene": null
				},
				{
					"id": 17,
					"name": "AA记账 - 结算方案",
					"pathName": "pages/tools/AA/solution/solution",
					"query": "",
					"scene": null
				}
			]
		}
	}
}